dtround
